<?xml version="1.0" encoding="UTF-8"?>
<con:operation id="73222137-908e-43b7-a3b1-f4af3403a352" isOneWay="false" action="" name="ListOfCountryNamesByName" bindingOperationName="ListOfCountryNamesByName" type="Request-Response" inputName="" receivesAttachments="false" sendsAttachments="false" anonymous="optional" xmlns:xsi="http://www.w3.org/2001/XMLSchema-instance" xmlns:con="http://eviware.com/soapui/config"><con:settings><con:setting id="73222137-908e-43b7-a3b1-f4af3403a352fileName">ListOfCountryNamesByName</con:setting></con:settings><con:call id="0d414754-2863-4ea2-be77-0e052c15948f" name="Request 1"><con:settings/><con:encoding>UTF-8</con:encoding><con:endpoint>http://webservices.oorsprong.org/websamples.countryinfo/CountryInfoService.wso</con:endpoint><con:request><![CDATA[<soapenv:Envelope xmlns:soapenv="http://schemas.xmlsoap.org/soap/envelope/" xmlns:web="http://www.oorsprong.org/websamples.countryinfo">\r
   <soapenv:Header/>\r
   <soapenv:Body>\r
      <web:ListOfCountryNamesByName/>\r
   </soapenv:Body>\r
</soapenv:Envelope>]]></con:request><con:credentials><con:selectedAuthProfile>No Authorization</con:selectedAuthProfile><con:authType>No Authorization</con:authType></con:credentials><con:wsaConfig mustUnderstand="NONE" version="200508" action="http://www.oorsprong.org/websamples.countryinfo/CountryInfoServiceSoapType/ListOfCountryNamesByNameRequest"/></con:call></con:operation>